load_xl/__init__.py
load_xl/cli.py
load_xl-1.0.1.dist-info/LICENSE.md
load_xl-1.0.1.dist-info/METADATA
load_xl-1.0.1.dist-info/WHEEL
load_xl-1.0.1.dist-info/entry_points.txt
load_xl-1.0.1.dist-info/top_level.txt
load_xl-1.0.1.dist-info/RECORD
