Metadata-Version: 2.1
Name: load_xl
Version: 1.0.1
Summary: A library for parsing configuration files, including .env, .ini, .yaml, .json, .toml, and .xml formats.
Home-page: https://github.com/sc4rfurry/load_xl
Author: sc4rfurry
Author-email: akalucifr@protonmail.ch
Keywords: config,configuration,parser,env,ini,yaml,json,toml,xml
Classifier: Development Status :: 5 - Production/Stable
Classifier: Intended Audience :: Developers
Classifier: Operating System :: OS Independent
Classifier: License :: OSI Approved :: MIT License
Classifier: Programming Language :: Python :: 3
Requires-Python: >=3.6
License-File: LICENSE.md
Requires-Dist: pyyaml
Requires-Dist: jsonschema
Requires-Dist: watchdog
Requires-Dist: toml
